QAPUBSUB/__init__.py
QAPUBSUB/base.py
QAPUBSUB/consumer.py
QAPUBSUB/debugtoool.py
QAPUBSUB/declaters.py
QAPUBSUB/producer.py
QAPUBSUB/setting.py
quantaxis_pubsub-1.11.dist-info/METADATA
quantaxis_pubsub-1.11.dist-info/WHEEL
quantaxis_pubsub-1.11.dist-info/entry_points.txt
quantaxis_pubsub-1.11.dist-info/top_level.txt
quantaxis_pubsub-1.11.dist-info/zip-safe
quantaxis_pubsub-1.11.dist-info/RECORD
